{
  "workflow_name": "PR Automation & Validation",
  "workflow_url": "https://github.com/drussell23/JARVIS/actions/runs/24996108503",
  "branch": "fix/ci/pr-automation-validation-run45650-20260427-125153",
  "commit_sha": "dfa23ab",
  "run_number": 45979,
  "failed_count": 5,
  "fix_branch": "fix/ci/pr-automation-validation-run45979-20260427-132309",
  "pr_title": "\ud83d\udea8 Fix CI/CD: PR Automation & Validation (Run #45979)",
  "analyses": [
    {
      "error_patterns": [
        {
          "pattern": "ERROR|Error|error",
          "matches": [
            {
              "line_number": 35,
              "content": "2026-04-27T13:02:31.9101322Z RequestError [HttpError]: API rate limit exceeded for installation. If you reach out to GitHub Support for help, please include the request ID 7C21:15299:4859C81:1253AA79:69EF5E67 and timestamp 2026-04-27 13:02:31 UTC. For more on scraping GitHub and how it may affect your rights, please review our Terms of Service (https://docs.github.com/en/site-policy/github-terms/github-terms-of-service)",
              "severity": "high",
              "emoji": "\u274c"
            },
            {
              "line_number": 36,
              "content": "2026-04-27T13:02:31.9111208Z ##[error]Unhandled error: HttpError: API rate limit exceeded for installation. If you reach out to GitHub Support for help, please include the request ID 7C21:15299:4859C81:1253AA79:69EF5E67 and timestamp 2026-04-27 13:02:31 UTC. For more on scraping GitHub and how it may affect your rights, please review our Terms of Service (https://docs.github.com/en/site-policy/github-terms/github-terms-of-service)",
              "severity": "high",
              "emoji": "\u274c"
            }
          ],
          "count": 2
        },
        {
          "pattern": "FAIL|Failed|failed",
          "matches": [
            {
              "line_number": 97,
              "content": "2026-04-27T13:02:32.0557239Z ##[warning]The process '/usr/bin/git' failed with exit code 128",
              "severity": "high",
              "emoji": "\ud83d\udca5"
            }
          ],
          "count": 1
        },
        {
          "pattern": "WARN|Warning|warning",
          "matches": [
            {
              "line_number": 97,
              "content": "2026-04-27T13:02:32.0557239Z ##[warning]The process '/usr/bin/git' failed with exit code 128",
              "severity": "medium",
              "emoji": "\u26a0\ufe0f"
            }
          ],
          "count": 1
        }
      ],
      "suggested_fixes": [
        "Review the logs above for specific error messages"
      ],
      "severity": "high",
      "category": "permission_error",
      "similar_failures": []
    },
    {
      "error_patterns": [
        {
          "pattern": "ERROR|Error|error",
          "matches": [
            {
              "line_number": 16,
              "content": "2026-04-27T13:02:17.8228191Z   subjectPatternError: The PR title must start with a capital letter.",
              "severity": "high",
              "emoji": "\u274c"
            },
            {
              "line_number": 28,
              "content": "2026-04-27T13:02:18.1275070Z ##[error]API rate limit exceeded for installation. If you reach out to GitHub Support for help, please include the request ID C7C1:14D252:3265862:3331D0B:69EF5E59 and timestamp 2026-04-27 13:02:18 UTC. For more on scraping GitHub and how it may affect your rights, please review our Terms of Service (https://docs.github.com/en/site-policy/github-terms/github-terms-of-service)",
              "severity": "high",
              "emoji": "\u274c"
            }
          ],
          "count": 2
        },
        {
          "pattern": "WARN|Warning|warning",
          "matches": [
            {
              "line_number": 30,
              "content": "2026-04-27T13:02:18.1817155Z ##[warning]Node.js 20 actions are deprecated. The following actions are running on Node.js 20 and may not work as expected: amannn/action-semantic-pull-request@v5. Actions will be forced to run with Node.js 24 by default starting June 2nd, 2026. Node.js 20 will be removed from the runner on September 16th, 2026. Please check if updated versions of these actions are available that support Node.js 24. To opt into Node.js 24 now, set the FORCE_JAVASCRIPT_ACTIONS_TO_NODE24=true environment variable on the runner or in your workflow file. Once Node.js 24 becomes the default, you can temporarily opt out by setting ACTIONS_ALLOW_USE_UNSECURE_NODE_VERSION=true. For more information see: https://github.blog/changelog/2025-09-19-deprecation-of-node-20-on-github-actions-runners/",
              "severity": "medium",
              "emoji": "\u26a0\ufe0f"
            }
          ],
          "count": 1
        },
        {
          "pattern": "timeout|timed out",
          "matches": [
            {
              "line_number": 20,
              "content": "- fix: Resolve database connection timeout",
              "severity": "medium",
              "emoji": "\u23f1\ufe0f"
            }
          ],
          "count": 1
        }
      ],
      "suggested_fixes": [
        "Consider increasing timeout values or optimizing slow operations",
        "Check service availability and network connectivity"
      ],
      "severity": "high",
      "category": "timeout",
      "similar_failures": []
    },
    {
      "error_patterns": [
        {
          "pattern": "ERROR|Error|error",
          "matches": [
            {
              "line_number": 43,
              "content": "2026-04-27T13:02:15.9384595Z RequestError [HttpError]: API rate limit exceeded for installation. If you reach out to GitHub Support for help, please include the request ID 8029:DBD94:49C9F46:12FC8B68:69EF5E57 and timestamp 2026-04-27 13:02:15 UTC. For more on scraping GitHub and how it may affect your rights, please review our Terms of Service (https://docs.github.com/en/site-policy/github-terms/github-terms-of-service)",
              "severity": "high",
              "emoji": "\u274c"
            },
            {
              "line_number": 44,
              "content": "2026-04-27T13:02:15.9429062Z ##[error]Unhandled error: HttpError: API rate limit exceeded for installation. If you reach out to GitHub Support for help, please include the request ID 8029:DBD94:49C9F46:12FC8B68:69EF5E57 and timestamp 2026-04-27 13:02:15 UTC. For more on scraping GitHub and how it may affect your rights, please review our Terms of Service (https://docs.github.com/en/site-policy/github-terms/github-terms-of-service)",
              "severity": "high",
              "emoji": "\u274c"
            }
          ],
          "count": 2
        }
      ],
      "suggested_fixes": [
        "Review the logs above for specific error messages"
      ],
      "severity": "high",
      "category": "permission_error",
      "similar_failures": []
    },
    {
      "error_patterns": [
        {
          "pattern": "ERROR|Error|error",
          "matches": [
            {
              "line_number": 45,
              "content": "2026-04-27T13:02:14.8569924Z RequestError [HttpError]: API rate limit exceeded for installation. If you reach out to GitHub Support for help, please include the request ID CC41:136CDC:10C0D2C:438D0D3:69EF5E56 and timestamp 2026-04-27 13:02:14 UTC. For more on scraping GitHub and how it may affect your rights, please review our Terms of Service (https://docs.github.com/en/site-policy/github-terms/github-terms-of-service)",
              "severity": "high",
              "emoji": "\u274c"
            },
            {
              "line_number": 46,
              "content": "2026-04-27T13:02:14.8616414Z ##[error]Unhandled error: HttpError: API rate limit exceeded for installation. If you reach out to GitHub Support for help, please include the request ID CC41:136CDC:10C0D2C:438D0D3:69EF5E56 and timestamp 2026-04-27 13:02:14 UTC. For more on scraping GitHub and how it may affect your rights, please review our Terms of Service (https://docs.github.com/en/site-policy/github-terms/github-terms-of-service)",
              "severity": "high",
              "emoji": "\u274c"
            }
          ],
          "count": 2
        },
        {
          "pattern": "WARN|Warning|warning",
          "matches": [
            {
              "line_number": 1,
              "content": "${warning}",
              "severity": "medium",
              "emoji": "\u26a0\ufe0f"
            }
          ],
          "count": 1
        }
      ],
      "suggested_fixes": [
        "Review the logs above for specific error messages"
      ],
      "severity": "high",
      "category": "permission_error",
      "similar_failures": []
    },
    {
      "error_patterns": [
        {
          "pattern": "ERROR|Error|error",
          "matches": [
            {
              "line_number": 45,
              "content": "2026-04-27T13:02:24.3603930Z RequestError [HttpError]: API rate limit exceeded for installation. If you reach out to GitHub Support for help, please include the request ID D029:37CF53:FDEF37:4027F62:69EF5E60 and timestamp 2026-04-27 13:02:24 UTC. For more on scraping GitHub and how it may affect your rights, please review our Terms of Service (https://docs.github.com/en/site-policy/github-terms/github-terms-of-service)",
              "severity": "high",
              "emoji": "\u274c"
            },
            {
              "line_number": 46,
              "content": "2026-04-27T13:02:24.3658731Z ##[error]Unhandled error: HttpError: API rate limit exceeded for installation. If you reach out to GitHub Support for help, please include the request ID D029:37CF53:FDEF37:4027F62:69EF5E60 and timestamp 2026-04-27 13:02:24 UTC. For more on scraping GitHub and how it may affect your rights, please review our Terms of Service (https://docs.github.com/en/site-policy/github-terms/github-terms-of-service)",
              "severity": "high",
              "emoji": "\u274c"
            }
          ],
          "count": 2
        }
      ],
      "suggested_fixes": [
        "Review the logs above for specific error messages"
      ],
      "severity": "high",
      "category": "permission_error",
      "similar_failures": []
    }
  ],
  "timestamp": "2026-04-27T13:23:09.718011"
}